odoo9_addon_hr_holidays_leave_auto_approve-9.0.1.0.0-py2.7-nspkg.pth
odoo_addons/hr_holidays_leave_auto_approve/__openerp__.py
odoo_addons/hr_holidays_leave_auto_approve/__init__.py
odoo_addons/hr_holidays_leave_auto_approve/README.rst
odoo_addons/hr_holidays_leave_auto_approve/models/hr_holidays.py
odoo_addons/hr_holidays_leave_auto_approve/models/hr_holidays_status.py
odoo_addons/hr_holidays_leave_auto_approve/models/__init__.py
odoo_addons/hr_holidays_leave_auto_approve/views/hr_holidays_status.xml
odoo_addons/hr_holidays_leave_auto_approve/tests/__init__.py
odoo_addons/hr_holidays_leave_auto_approve/tests/test_hr_holidays_leave_auto_approve.py
odoo9_addon_hr_holidays_leave_auto_approve-9.0.1.0.0.dist-info/top_level.txt
odoo9_addon_hr_holidays_leave_auto_approve-9.0.1.0.0.dist-info/WHEEL
odoo9_addon_hr_holidays_leave_auto_approve-9.0.1.0.0.dist-info/RECORD
odoo9_addon_hr_holidays_leave_auto_approve-9.0.1.0.0.dist-info/metadata.json
odoo9_addon_hr_holidays_leave_auto_approve-9.0.1.0.0.dist-info/DESCRIPTION.rst
odoo9_addon_hr_holidays_leave_auto_approve-9.0.1.0.0.dist-info/METADATA
odoo9_addon_hr_holidays_leave_auto_approve-9.0.1.0.0.dist-info/namespace_packages.txt
